{
  "Model": "Items/Tools/Switch_Control.blockymodel",
  "Texture": "Items/Tools/Switch_Controller.png",
  "Icon": "Icons/ItemsGenerated/Switch_Controller.png",
  "IconProperties": {
    "Scale": 0.8,
    "Rotation": [
      28,
      45,
      22.5
    ],
    "Translation": [
      1,
      -6
    ]
  },
  "MaxStack": 1,
  "PlayerAnimationsId": "Item_Controller",
  "Interactions": {
    "Primary": {
      "Interactions": [
        {
          "Type": "SwitchController"
        }
      ]
    },
    "Use": {
      "Interactions": [
        {
          "Type": "Serial",
          "Interactions": [
            {
              "Type": "Simple",
              "Effects": {
                "ItemAnimationId": "PushController"
              },
              "RunTime": 0.2
            },
            {
              "Type": "SwitchWirelessLights"
            }
          ]
        }
      ],
      "RequireNewClick": true
    }
  },
  "TranslationProperties": {
    "Name": "Switch_Controller"
  },
  "Quality": "Rare",
  "Categories": [
    "Items.Tools"
  ],
  "Recipe": {
    "BenchRequirement": [
      {
        "Id": "Workbench",
        "Categories": [
          "Workbench_Tools"
        ]
      }
    ],
    "OutputQuantity": 1,
    "Input": [
      {
        "ItemId": "Ingredient_Bar_Iron",
        "Quantity": 2
      },
      {
        "ItemId": "Ingredient_Bar_Copper",
        "Quantity": 4
      },
      {
        "ItemId": "Rock_Gem_Emerald",
        "Quantity": 1
      }
    ]
  },
  "UsePlayerAnimations": true,
  "Animation": "Items/Tools/Switch_Controller_Idle.blockyanim"
}
